{
  "sourceFile": "door_lab_wall.map",
  "totalBytes": 1020,
  "fileHeader": {
    "RES_Magic": "RES ",
    "mapSize": 1012,
    "MAP_Magic": "MAP "
  },
  "GRPH": {
    "GRPH_Magic": "GRPH",
    "graphSize": 36,
    "options": "0x80000000",
    "packedDiff": 0,
    "subresourceCount": 1,
    "envSize": 20,
    "isShadow": 0,
    "gammaDarker": "0x000000",
    "gammaLighter": "0x000000",
    "windDirection": 200,
    "windSpeed": 0.02500000037252903
  },
  "HEAD": {
    "HEAD_Magic": "HEAD",
    "headSize": 40,
    "options": "0x80000000",
    "packedDiff": 0,
    "subresourceCount": 1,
    "mapInfoSize": 24,
    "mapSizeX": 1200.0,
    "mapSizeY": 1200.0,
    "mapCameraX": 228.0,
    "mapCameraY": 186.0,
    "currentTime": 269722,
    "version": "0x0C"
  },
  "SPR": {
    "SPR_Magic": "SPR ",
    "sprSize": 524,
    "options": "0x80000000",
    "packedDiff": 0,
    "subresourceCount": 1,
    "sprInfoSize": 508,
    "spriteCount": 18,
    "sprites": [
      {
        "objectId": 20318424,
        "vid": 651,
        "posX": 247.0,
        "posY": 496.0,
        "posZ": 0.0,
        "direction": 0,
        "army": 0
      },
      {
        "objectId": 20317920,
        "vid": 651,
        "posX": 427.0,
        "posY": 368.0,
        "posZ": 0.0,
        "direction": 0,
        "army": 0
      },
      {
        "objectId": 20317752,
        "vid": 651,
        "posX": 607.0,
        "posY": 240.0,
        "posZ": 0.0,
        "direction": 0,
        "army": 0
      },
      {
        "objectId": 20317584,
        "vid": 650,
        "posX": 247.0,
        "posY": 560.0,
        "posZ": 0.0,
        "direction": 0,
        "army": 0
      },
      {
        "objectId": 20317416,
        "vid": 650,
        "posX": 427.0,
        "posY": 688.0,
        "posZ": 0.0,
        "direction": 0,
        "army": 0
      },
      {
        "objectId": 20317248,
        "vid": 650,
        "posX": 607.0,
        "posY": 816.0,
        "posZ": 0.0,
        "direction": 0,
        "army": 0
      },
      {
        "objectId": 20317080,
        "vid": 650,
        "posX": 787.0,
        "posY": 944.0,
        "posZ": 0.0,
        "direction": 0,
        "army": 0
      },
      {
        "objectId": 20316912,
        "vid": 651,
        "posX": 787.0,
        "posY": 112.0,
        "posZ": 0.0,
        "direction": 0,
        "army": 0
      },
      {
        "objectId": 20316744,
        "vid": 653,
        "posX": 337.0,
        "posY": 624.0,
        "posZ": 0.0,
        "direction": 0,
        "army": 0
      },
      {
        "objectId": 20316264,
        "vid": 653,
        "posX": 517.0,
        "posY": 752.0,
        "posZ": 0.0,
        "direction": 0,
        "army": 0
      },
      {
        "objectId": 297103944,
        "vid": 653,
        "posX": 337.0,
        "posY": 432.0,
        "posZ": 0.0,
        "direction": 64,
        "army": 0
      },
      {
        "objectId": 297103776,
        "vid": 653,
        "posX": 517.0,
        "posY": 304.0,
        "posZ": 0.0,
        "direction": 64,
        "army": 0
      },
      {
        "objectId": 297103608,
        "vid": 654,
        "posX": 697.0,
        "posY": 176.0,
        "posZ": 0.0,
        "direction": 64,
        "army": 0
      },
      {
        "objectId": 297103296,
        "vid": 654,
        "posX": 697.0,
        "posY": 880.0,
        "posZ": 0.0,
        "direction": 0,
        "army": 0
      },
      {
        "objectId": 297108656,
        "vid": 164,
        "posX": 513.0,
        "posY": 288.0,
        "posZ": 0.0,
        "direction": 128,
        "army": 0
      },
      {
        "objectId": 297107960,
        "vid": 164,
        "posX": 342.0,
        "posY": 413.0,
        "posZ": 0.0,
        "direction": 128,
        "army": 0
      },
      {
        "objectId": 297107120,
        "vid": 164,
        "posX": 519.0,
        "posY": 735.0,
        "posZ": 0.0,
        "direction": 0,
        "army": 0
      },
      {
        "objectId": 297106320,
        "vid": 164,
        "posX": 334.0,
        "posY": 606.0,
        "posZ": 0.0,
        "direction": 0,
        "army": 0
      }
    ],
    "terminator": "0xFFFFFFFF"
  },
  "SPRD": {
    "SPRD_Magic": "SPRD",
    "sprdSize": 308,
    "options": "0x80000000",
    "packedDiff": 0,
    "subresourceCount": 19,
    "subs": [
      {
        "subSize": 12,
        "isTerminator": false,
        "objectId": 20318424,
        "commandStack": {
          "cmdCount": 0,
          "commands": []
        },
        "dropList": {
          "itemCount": 0,
          "itemVids": []
        }
      },
      {
        "subSize": 12,
        "isTerminator": false,
        "objectId": 20317920,
        "commandStack": {
          "cmdCount": 0,
          "commands": []
        },
        "dropList": {
          "itemCount": 0,
          "itemVids": []
        }
      },
      {
        "subSize": 12,
        "isTerminator": false,
        "objectId": 20317752,
        "commandStack": {
          "cmdCount": 0,
          "commands": []
        },
        "dropList": {
          "itemCount": 0,
          "itemVids": []
        }
      },
      {
        "subSize": 12,
        "isTerminator": false,
        "objectId": 20317584,
        "commandStack": {
          "cmdCount": 0,
          "commands": []
        },
        "dropList": {
          "itemCount": 0,
          "itemVids": []
        }
      },
      {
        "subSize": 12,
        "isTerminator": false,
        "objectId": 20317416,
        "commandStack": {
          "cmdCount": 0,
          "commands": []
        },
        "dropList": {
          "itemCount": 0,
          "itemVids": []
        }
      },
      {
        "subSize": 12,
        "isTerminator": false,
        "objectId": 20317248,
        "commandStack": {
          "cmdCount": 0,
          "commands": []
        },
        "dropList": {
          "itemCount": 0,
          "itemVids": []
        }
      },
      {
        "subSize": 12,
        "isTerminator": false,
        "objectId": 20317080,
        "commandStack": {
          "cmdCount": 0,
          "commands": []
        },
        "dropList": {
          "itemCount": 0,
          "itemVids": []
        }
      },
      {
        "subSize": 12,
        "isTerminator": false,
        "objectId": 20316912,
        "commandStack": {
          "cmdCount": 0,
          "commands": []
        },
        "dropList": {
          "itemCount": 0,
          "itemVids": []
        }
      },
      {
        "subSize": 12,
        "isTerminator": false,
        "objectId": 20316744,
        "commandStack": {
          "cmdCount": 0,
          "commands": []
        },
        "dropList": {
          "itemCount": 0,
          "itemVids": []
        }
      },
      {
        "subSize": 12,
        "isTerminator": false,
        "objectId": 20316264,
        "commandStack": {
          "cmdCount": 0,
          "commands": []
        },
        "dropList": {
          "itemCount": 0,
          "itemVids": []
        }
      },
      {
        "subSize": 12,
        "isTerminator": false,
        "objectId": 297103944,
        "commandStack": {
          "cmdCount": 0,
          "commands": []
        },
        "dropList": {
          "itemCount": 0,
          "itemVids": []
        }
      },
      {
        "subSize": 12,
        "isTerminator": false,
        "objectId": 297103776,
        "commandStack": {
          "cmdCount": 0,
          "commands": []
        },
        "dropList": {
          "itemCount": 0,
          "itemVids": []
        }
      },
      {
        "subSize": 12,
        "isTerminator": false,
        "objectId": 297103608,
        "commandStack": {
          "cmdCount": 0,
          "commands": []
        },
        "dropList": {
          "itemCount": 0,
          "itemVids": []
        }
      },
      {
        "subSize": 12,
        "isTerminator": false,
        "objectId": 297103296,
        "commandStack": {
          "cmdCount": 0,
          "commands": []
        },
        "dropList": {
          "itemCount": 0,
          "itemVids": []
        }
      },
      {
        "subSize": 12,
        "isTerminator": false,
        "objectId": 297108656,
        "commandStack": {
          "cmdCount": 0,
          "commands": []
        },
        "dropList": {
          "itemCount": 0,
          "itemVids": []
        }
      },
      {
        "subSize": 12,
        "isTerminator": false,
        "objectId": 297107960,
        "commandStack": {
          "cmdCount": 0,
          "commands": []
        },
        "dropList": {
          "itemCount": 0,
          "itemVids": []
        }
      },
      {
        "subSize": 12,
        "isTerminator": false,
        "objectId": 297107120,
        "commandStack": {
          "cmdCount": 0,
          "commands": []
        },
        "dropList": {
          "itemCount": 0,
          "itemVids": []
        }
      },
      {
        "subSize": 12,
        "isTerminator": false,
        "objectId": 297106320,
        "commandStack": {
          "cmdCount": 0,
          "commands": []
        },
        "dropList": {
          "itemCount": 0,
          "itemVids": []
        }
      },
      {
        "subSize": 4,
        "isTerminator": true,
        "terminator": "0xFFFFFFFF"
      }
    ]
  },
  "PLAY": {
    "PLAY_Magic": "PLAY",
    "playSize": 32,
    "options": "0x80000000",
    "packedDiff": 0,
    "subresourceCount": 1,
    "playInfoSize": 16,
    "player1_ObjectId": 0,
    "player2_ObjectId": 0,
    "player3_ObjectId": 0,
    "player4_ObjectId": 0
  },
  "GROU": {
    "GROU_Magic": "GROU",
    "groupSize": 20,
    "options": "0x80000000",
    "packedDiff": 0,
    "subresourceCount": 1,
    "groupInfoSize": 4,
    "groups": [],
    "globalTerminator": "0xFFFFFFFF"
  }
}